Metadata-Version: 1.0
Name: tpscompare
Version: 0.1
Summary: Compare Monaco output to Mephisto measurements
Home-page: UNKNOWN
Author: Simon Biggs
Author-email: mail@simonbiggs.net
License: AGPL3+
Platform: UNKNOWN
